mazalib.cp39-win_amd64.pyd
eigen3/.hg_archival.txt
eigen3/.hgeol
eigen3/.hgignore
eigen3/.hgtags
eigen3/CMakeLists.txt
eigen3/COPYING.BSD
eigen3/COPYING.GPL
eigen3/COPYING.LGPL
eigen3/COPYING.MINPACK
eigen3/COPYING.MPL2
eigen3/COPYING.README
eigen3/CTestConfig.cmake
eigen3/CTestCustom.cmake.in
eigen3/INSTALL
eigen3/README.md
eigen3/__init__.py
eigen3/eigen3.pc.in
eigen3/signature_of_eigen3_matrix_library
eigen3/Eigen/CMakeLists.txt
eigen3/Eigen/Cholesky
eigen3/Eigen/CholmodSupport
eigen3/Eigen/Core
eigen3/Eigen/Dense.h
eigen3/Eigen/Eigen
eigen3/Eigen/Eigenvalues
eigen3/Eigen/Geometry
eigen3/Eigen/Householder
eigen3/Eigen/IterativeLinearSolvers
eigen3/Eigen/Jacobi
eigen3/Eigen/KLUSupport
eigen3/Eigen/LU
eigen3/Eigen/MetisSupport
eigen3/Eigen/OrderingMethods
eigen3/Eigen/PaStiXSupport
eigen3/Eigen/PardisoSupport
eigen3/Eigen/QR
eigen3/Eigen/QtAlignedMalloc
eigen3/Eigen/SPQRSupport
eigen3/Eigen/SVD
eigen3/Eigen/Sparse
eigen3/Eigen/SparseCholesky
eigen3/Eigen/SparseCore
eigen3/Eigen/SparseLU
eigen3/Eigen/SparseQR
eigen3/Eigen/StdDeque
eigen3/Eigen/StdList
eigen3/Eigen/StdVector
eigen3/Eigen/SuperLUSupport
eigen3/Eigen/UmfPackSupport
eigen3/Eigen/src/Cholesky/LDLT.h
eigen3/Eigen/src/Cholesky/LLT.h
eigen3/Eigen/src/Cholesky/LLT_LAPACKE.h
eigen3/Eigen/src/CholmodSupport/CholmodSupport.h
eigen3/Eigen/src/Core/ArithmeticSequence.h
eigen3/Eigen/src/Core/Array.h
eigen3/Eigen/src/Core/ArrayBase.h
eigen3/Eigen/src/Core/ArrayWrapper.h
eigen3/Eigen/src/Core/Assign.h
eigen3/Eigen/src/Core/AssignEvaluator.h
eigen3/Eigen/src/Core/Assign_MKL.h
eigen3/Eigen/src/Core/BandMatrix.h
eigen3/Eigen/src/Core/Block.h
eigen3/Eigen/src/Core/BooleanRedux.h
eigen3/Eigen/src/Core/CommaInitializer.h
eigen3/Eigen/src/Core/ConditionEstimator.h
eigen3/Eigen/src/Core/CoreEvaluators.h
eigen3/Eigen/src/Core/CoreIterators.h
eigen3/Eigen/src/Core/CwiseBinaryOp.h
eigen3/Eigen/src/Core/CwiseNullaryOp.h
eigen3/Eigen/src/Core/CwiseTernaryOp.h
eigen3/Eigen/src/Core/CwiseUnaryOp.h
mazalib-0.50.dist-info/LICENSE.txt
mazalib-0.50.dist-info/METADATA
mazalib-0.50.dist-info/WHEEL
mazalib-0.50.dist-info/entry_points.txt
mazalib-0.50.dist-info/top_level.txt
mazalib-0.50.dist-info/RECORD
