Metadata-Version: 2.1
Name: mazalib
Version: 0.50
Summary: Cross-platform 2d/3d image segmentation C++ library
Home-page: UNKNOWN
Author: Mathieu Gravey, Roman V. Vasilyev, Timofey Sizonenko, Kirill M. Gerke, Marina V. Karsanina, Andrey A. Ananev
Author-email: mathieu.gravey@unil.ch
License: GPLv3
Platform: UNKNOWN
Classifier: Development Status :: 3 - Alpha
Classifier: Intended Audience :: Science/Research
Classifier: Intended Audience :: Education
Classifier: License :: OSI Approved :: GNU Lesser General Public License v3 (LGPLv3)
Classifier: Programming Language :: C++
Classifier: Programming Language :: Python :: 3 :: Only
Requires-Dist: numpy
